noteproxy/__init__.py
noteproxy/core.py
noteproxy/database.py
noteproxy/job.py
noteproxy/run.py
noteproxy-0.0.3.dist-info/LICENSE
noteproxy-0.0.3.dist-info/METADATA
noteproxy-0.0.3.dist-info/WHEEL
noteproxy-0.0.3.dist-info/top_level.txt
noteproxy-0.0.3.dist-info/RECORD
