Metadata-Version: 2.1
Name: noteproxy
Version: 0.0.3
Summary: noteproxy
Home-page: https://github.com/1007530194
Author: niuliangtao
Author-email: 1007530194@qq.com
License: UNKNOWN
Platform: UNKNOWN
